{
  "round_matrix_density": 0.01318359375,
  "round_matrix_rank": 256,
  "evolution": [
    {
      "r": 1,
      "density": 0.01318359375,
      "rank": 256
    },
    {
      "r": 2,
      "density": 0.0439453125,
      "rank": 256
    },
    {
      "r": 3,
      "density": 0.10595703125,
      "rank": 256
    },
    {
      "r": 4,
      "density": 0.1904296875,
      "rank": 256,
      "kernel_dim": 0
    },
    {
      "r": 5,
      "density": 0.27294921875,
      "rank": 256
    },
    {
      "r": 6,
      "density": 0.3505859375,
      "rank": 256
    },
    {
      "r": 8,
      "density": 0.44921875,
      "rank": 256,
      "kernel_dim": 0
    },
    {
      "r": 10,
      "density": 0.509765625,
      "rank": 256
    },
    {
      "r": 12,
      "density": 0.509765625,
      "rank": 256
    },
    {
      "r": 14,
      "density": 0.49609375,
      "rank": 256
    },
    {
      "r": 16,
      "density": 0.486328125,
      "rank": 256,
      "kernel_dim": 0
    },
    {
      "r": 17,
      "density": 0.470703125,
      "rank": 256
    },
    {
      "r": 18,
      "density": 0.4853515625,
      "rank": 256
    },
    {
      "r": 19,
      "density": 0.48291015625,
      "rank": 256
    },
    {
      "r": 20,
      "density": 0.4853515625,
      "rank": 256,
      "kernel_dim": 0
    },
    {
      "r": 22,
      "density": 0.4755859375,
      "rank": 256
    },
    {
      "r": 24,
      "density": 0.4775390625,
      "rank": 256,
      "kernel_dim": 0
    },
    {
      "r": 28,
      "density": 0.466796875,
      "rank": 256
    },
    {
      "r": 32,
      "density": 0.4755859375,
      "rank": 256,
      "kernel_dim": 0
    },
    {
      "r": 40,
      "density": 0.5,
      "rank": 256
    },
    {
      "r": 48,
      "density": 0.4736328125,
      "rank": 256
    },
    {
      "r": 56,
      "density": 0.4912109375,
      "rank": 256
    },
    {
      "r": 64,
      "density": 0.4931640625,
      "rank": 256
    }
  ],
  "full_density_round": 10,
  "runtime_sec": 1.6273226737976074
}